LICENSE
MANIFEST.in
README.rst
requirements.txt
setup.py
bin/tse2sql
bin/tse2sql-scrapper
lib/tse2sql/__init__.py
lib/tse2sql/args.py
lib/tse2sql/main.py
lib/tse2sql/readers.py
lib/tse2sql/render.py
lib/tse2sql/scrapper.py
lib/tse2sql/utils.py
lib/tse2sql.egg-info/PKG-INFO
lib/tse2sql.egg-info/SOURCES.txt
lib/tse2sql.egg-info/dependency_links.txt
lib/tse2sql.egg-info/requires.txt
lib/tse2sql.egg-info/top_level.txt
lib/tse2sql/renderers/__init__.py
lib/tse2sql/renderers/mysql.py