Metadata-Version: 1.1
Name: tse2sql
Version: 1.1.0
Summary: SQL converter of the electoral registry published by the Costa Rican Supreme Electoral Tribunal.
Home-page: https://tse2sql.readthedocs.org/
Author: Carlos Jenkins
Author-email: carlos@jenkins.co.cr
License: UNKNOWN
Keywords: tse2sql
Platform: UNKNOWN
Classifier: Development Status :: 3 - Alpha
Classifier: Intended Audience :: Developers
Classifier: License :: OSI Approved :: Apache Software License
Classifier: Natural Language :: English
Classifier: Operating System :: POSIX :: Linux
Classifier: Programming Language :: Python :: 2
Classifier: Programming Language :: Python :: 2.7
Classifier: Programming Language :: Python :: 3
Classifier: Programming Language :: Python :: 3.4
